chinesename/__init__.py
chinesename/chinesename.py
chinesename/source/boy.json
chinesename/source/firstnames.txt
chinesename/source/girl.json
chinesename/source/gushiwen.json
chinesename/source/lastnames.txt
tests/__init__.py
tests/test_chinesename.py
chinesename-0.1.1.dist-info/METADATA
chinesename-0.1.1.dist-info/WHEEL
chinesename-0.1.1.dist-info/top_level.txt
chinesename-0.1.1.dist-info/zip-safe
chinesename-0.1.1.dist-info/RECORD
